amodule.py
sampleproject/__init__.py
sampleproject/__main__.py
sampleproject/cli_int1.py
sampleproject/libs/__init__.py
sampleproject/libs/samplemodule.py
Adversary_Armor-0.1.1.dist-info/LICENSE
Adversary_Armor-0.1.1.dist-info/METADATA
Adversary_Armor-0.1.1.dist-info/WHEEL
Adversary_Armor-0.1.1.dist-info/top_level.txt
Adversary_Armor-0.1.1.dist-info/RECORD
